soiltextureplot/__init__.py
soiltextureplot/classifier.py
soiltextureplot/datasets.py
soiltextureplot/plotting.py
soiltextureplot/systems.py
soiltextureplot/triangle.py
soiltextureplot/utils.py
soiltextureplot-0.1.0.dist-info/licenses/LICENSE
soiltextureplot-0.1.0.dist-info/METADATA
soiltextureplot-0.1.0.dist-info/WHEEL
soiltextureplot-0.1.0.dist-info/top_level.txt
soiltextureplot-0.1.0.dist-info/RECORD
