Metadata-Version: 2.4
Name: soiltextureplot
Version: 0.1.0
Summary: Soil texture triangle plotting and classification
Author-email: Amninder Singh <amnindersingh13@gmail.com>
License: MIT License
Project-URL: Homepage, https://github.com/singhamninder/soiltextureplot
Project-URL: Bug Tracker, https://github.com/singhamninder/soiltextureplot/issues
Keywords: soil,texture,triangle,plot,classification,ternary
Classifier: Development Status :: 4 - Beta
Classifier: Intended Audience :: Science/Research
Classifier: License :: OSI Approved :: MIT License
Classifier: Programming Language :: Python :: 3
Classifier: Programming Language :: Python :: 3.9
Classifier: Programming Language :: Python :: 3.10
Classifier: Programming Language :: Python :: 3.11
Classifier: Programming Language :: Python :: 3.12
Classifier: Topic :: Scientific/Engineering
Requires-Python: >=3.9
License-File: LICENSE
Requires-Dist: pandas>=1.5.0
Requires-Dist: numpy>=1.23.0
Requires-Dist: matplotlib>=3.7.0
Requires-Dist: mpltern>=1.0.0
Dynamic: license-file
